Metadata-Version: 1.0
Name: bonifacio-probability
Version: 0.1
Summary: Binomial and Gaussian distributions
Home-page: UNKNOWN
Author: Luis Bonifacio
Author-email: luis.g.bonifacio@gmail.com
License: UNKNOWN
Platform: UNKNOWN
